FareedLib/__init__.py
FareedLib/core_module.py
FareedLib/other_moules.py
tests/__init__.py
tests/test_core_module.py
FareedLib-0.2.1.dist-info/METADATA
FareedLib-0.2.1.dist-info/WHEEL
FareedLib-0.2.1.dist-info/top_level.txt
FareedLib-0.2.1.dist-info/RECORD
