Metadata-Version: 2.1
Name: FareedLib
Version: 0.2.1
Summary: A library with common utilities for string manipulation, list filtering, and basic math operations
Home-page: https://github.com/MrFalafel/FareedLib
Author: Fareed
Author-email: no-email@MrFalafel.com
Classifier: Programming Language :: Python :: 3
Classifier: License :: OSI Approved :: MIT License
Classifier: Operating System :: OS Independent
Requires-Python: >=3.6
